as_search/__init__.py
as_search/__main__.py
as_search/asn_db.py
as_search/version.py
as_search-0.0.2.dist-info/LICENSE
as_search-0.0.2.dist-info/METADATA
as_search-0.0.2.dist-info/WHEEL
as_search-0.0.2.dist-info/entry_points.txt
as_search-0.0.2.dist-info/top_level.txt
as_search-0.0.2.dist-info/RECORD
