Metadata-Version: 2.1
Name: as-search
Version: 0.0.2
Summary: Search info in Autonomous System database
Home-page: https://gitlab.com/Zer1t0/as-search
Author: Eloy Pérez González
Classifier: Programming Language :: Python :: 3
Classifier: License :: OSI Approved :: GNU General Public License v3 (GPLv3)
License-File: LICENSE
Requires-Dist: requests
Requires-Dist: bs4
Requires-Dist: pandas
Requires-Dist: tqdm
